odoo/addons/sql_export_excel/README.rst
odoo/addons/sql_export_excel/__init__.py
odoo/addons/sql_export_excel/__manifest__.py
odoo/addons/sql_export_excel/i18n/sql_export_excel.pot
odoo/addons/sql_export_excel/models/__init__.py
odoo/addons/sql_export_excel/models/sql_export.py
odoo/addons/sql_export_excel/readme/CONFIGURE.rst
odoo/addons/sql_export_excel/readme/CONTRIBUTORS.rst
odoo/addons/sql_export_excel/readme/DESCRIPTION.rst
odoo/addons/sql_export_excel/static/description/icon.png
odoo/addons/sql_export_excel/static/description/index.html
odoo/addons/sql_export_excel/tests/__init__.py
odoo/addons/sql_export_excel/tests/test_sql_query_excel.py
odoo/addons/sql_export_excel/views/sql_export_view.xml
odoo12_addon_sql_export_excel-12.0.1.1.1.dist-info/METADATA
odoo12_addon_sql_export_excel-12.0.1.1.1.dist-info/WHEEL
odoo12_addon_sql_export_excel-12.0.1.1.1.dist-info/top_level.txt
odoo12_addon_sql_export_excel-12.0.1.1.1.dist-info/RECORD
