Metadata-Version: 2.1
Name: odoo12-addon-sql-export-excel
Version: 12.0.1.1.1
Summary: Allow to export a sql query to an excel file.
Home-page: https://github.com/OCA/server-tools
Author: Akretion,Odoo Community Association (OCA)
Author-email: support@odoo-community.org
License: AGPL-3
Platform: UNKNOWN
Classifier: Programming Language :: Python
Classifier: Framework :: Odoo
Classifier: Framework :: Odoo :: 12.0
Classifier: License :: OSI Approved :: GNU Affero General Public License v3
Requires-Python: >=3.5
Requires-Dist: odoo12-addon-sql-export
Requires-Dist: odoo <12.1dev,>=12.0a
Requires-Dist: openpyxl
